vals/__init__.py
vals/cli/__init__.py
vals/cli/main.py
vals/cli/project.py
vals/cli/run.py
vals/cli/suite.py
vals/cli/util.py
vals/graphql/evaluate_test_checks.graphql
vals/graphql/custom_metrics/mutations.graphql
vals/graphql/custom_metrics/queries.graphql
vals/graphql/fragments/qa_sets.graphql
vals/graphql/fragments/run.graphql
vals/graphql/fragments/shared.graphql
vals/graphql/fragments/test.graphql
vals/graphql/human_review/AddAllToQueue.graphql
vals/graphql/human_review/GetSingleRunReview.graphql
vals/graphql/human_review/GetSingleTestResultReviewWithCount.graphql
vals/graphql/human_review/GetUserOptions.graphql
vals/graphql/human_review/ModifyQueue.graphql
vals/graphql/projects/queries.graphql
vals/graphql/qa_sets/mutations.graphql
vals/graphql/qa_sets/queries.graphql
vals/graphql/runs/mutations.graphql
vals/graphql/runs/queries.graphql
vals/graphql/suites/mutations.graphql
vals/graphql/suites/queries.graphql
vals/graphql_client/__init__.py
vals/graphql_client/add_all_tests_to_queue_single.py
vals/graphql_client/add_batch_tests.py
vals/graphql_client/add_or_remove_users_to_run_review.py
vals/graphql_client/async_base_client.py
vals/graphql_client/base_model.py
vals/graphql_client/batch_add_question_answer_pairs.py
vals/graphql_client/client.py
vals/graphql_client/create_empty_run_object.py
vals/graphql_client/create_or_update_test_suite.py
vals/graphql_client/create_question_answer_pair.py
vals/graphql_client/create_question_answer_set.py
vals/graphql_client/delete_test_suite.py
vals/graphql_client/edit_custom_metric.py
vals/graphql_client/enums.py
vals/graphql_client/evaluate_test_checks.py
vals/graphql_client/exceptions.py
vals/graphql_client/fragments.py
vals/graphql_client/get_active_custom_operators.py
vals/graphql_client/get_custom_metric.py
vals/graphql_client/get_default_parameters.py
vals/graphql_client/get_operators.py
vals/graphql_client/get_run_dataframe.py
vals/graphql_client/get_run_status.py
vals/graphql_client/get_single_run_review.py
valsai-0.3.8.dist-info/METADATA
valsai-0.3.8.dist-info/WHEEL
valsai-0.3.8.dist-info/entry_points.txt
valsai-0.3.8.dist-info/top_level.txt
valsai-0.3.8.dist-info/RECORD
