Metadata-Version: 2.4
Name: valsai
Version: 0.3.8
Summary: SDK for the Vals AI Platform
Author: Langston Nashold, Rayan Krishnan
License: MIT
Requires-Python: >=3.11
Requires-Dist: Click
Requires-Dist: gql
Requires-Dist: tqdm
Requires-Dist: requests
Requires-Dist: pandas
Requires-Dist: descope
Requires-Dist: pydantic
Requires-Dist: httpx
Requires-Dist: tabulate
Requires-Dist: inspect-ai
Requires-Dist: aiohttp
Requires-Dist: aiofiles
Requires-Dist: pytest-asyncio>=1.1.0
Requires-Dist: asyncstdlib>=3.13.1
Requires-Dist: opentelemetry-api
Requires-Dist: opentelemetry-sdk
Requires-Dist: opentelemetry-exporter-otlp
Requires-Dist: opentelemetry-instrumentation
Requires-Dist: model-library
